MANIFEST.in
README.txt
setup.py
docs/HISTORY.txt
docs/INSTALL.txt
docs/LICENSE.GPL
docs/LICENSE.txt
rer/__init__.py
rer.giunta.egg-info/PKG-INFO
rer.giunta.egg-info/SOURCES.txt
rer.giunta.egg-info/dependency_links.txt
rer.giunta.egg-info/entry_points.txt
rer.giunta.egg-info/namespace_packages.txt
rer.giunta.egg-info/not-zip-safe
rer.giunta.egg-info/requires.txt
rer.giunta.egg-info/top_level.txt
rer/giunta/README.txt
rer/giunta/__init__.py
rer/giunta/config.py
rer/giunta/configure.zcml
rer/giunta/i18n.sh
rer/giunta/upgrades.py
rer/giunta/upgrades.zcml
rer/giunta/browser/__init__.py
rer/giunta/browser/assessore.css
rer/giunta/browser/assessore.png
rer/giunta/browser/assessore_header_viewlet.pt
rer/giunta/browser/assessore_header_viewlet.py
rer/giunta/browser/assessore_view.pt
rer/giunta/browser/configure.zcml
rer/giunta/content/__init__.py
rer/giunta/content/assessore.py
rer/giunta/content/configure.zcml
rer/giunta/interfaces/__init__.py
rer/giunta/interfaces/assessore.py
rer/giunta/interfaces/layer.py
rer/giunta/interfaces/viewlet_manager.py
rer/giunta/locales/rer.giunta.pot
rer/giunta/locales/it/LC_MESSAGES/rer.giunta.mo
rer/giunta/locales/it/LC_MESSAGES/rer.giunta.po
rer/giunta/profiles/default/browserlayer.xml
rer/giunta/profiles/default/catalog.xml
rer/giunta/profiles/default/cssregistry.xml
rer/giunta/profiles/default/factorytool.xml
rer/giunta/profiles/default/metadata.xml
rer/giunta/profiles/default/rolemap.xml
rer/giunta/profiles/default/tinymce.xml
rer/giunta/profiles/default/types.xml
rer/giunta/profiles/default/viewlets.xml
rer/giunta/profiles/default/types/RERAssessore.xml
rer/giunta/tests/__init__.py
rer/giunta/tests/base.py
rer/giunta/tests/test_doctest.py